lib/__init__.py
lib/cors.py
CORS_Analyzer-1.0.9.dist-info/METADATA
CORS_Analyzer-1.0.9.dist-info/WHEEL
CORS_Analyzer-1.0.9.dist-info/entry_points.txt
CORS_Analyzer-1.0.9.dist-info/top_level.txt
CORS_Analyzer-1.0.9.dist-info/RECORD
