Metadata-Version: 2.1
Name: CORS-Analyzer
Version: 1.0.9
Summary: The cors-analyzer package is used to find the vulnerable CORS domains
Home-page: UNKNOWN
Author: Hariharan
License: UNKNOWN
Keywords: cors,cors-finder,cors-analyzer,cors misconfiguration,cors exploit,cors vulnerability
Platform: UNKNOWN
